{"songname":"","newanswer":"saika","songname1":"blowmymindtpzoverheatremix","songname2":"obey","songname3":"djmashiroisdeadoralive","songname4":"reverie","songname5":"realize","songname6":"utopia","songanswer":"hi","songanswer1":"blowmymindtpzoverheatremix","songanswer2":"obey","songanswer3":"djmashiroisdeadoralive","songanswer4":"reverie","songanswer5":"realize","songanswer6":"utopia","isnormal":false,"isscrambled":true,"ishardmode":false,"ischromatic":true,"isreverse":false,"isduo":false,"isfragmented":false,"isquad":false,"newCytusHeardle":true,"usedCommands":[],"title":"CHROMATIC SCRAMBLED Cytus Heardle #19:"}